Rest_Utils-1.2.6.data/data/requirements.txt
rest_utils/__init__.py
rest_utils/date.py
rest_utils/decorators.py
rest_utils/error_route.py
rest_utils/exception.py
rest_utils/exp_format.py
rest_utils/fields.py
rest_utils/flask_engine.py
rest_utils/flask_trace.py
rest_utils/log.py
rest_utils/manager.py
rest_utils/params.py
rest_utils/py3to2.py
rest_utils/sa_util.py
rest_utils/schema.py
rest_utils/static.py
rest_utils/libs/__init__.py
rest_utils/libs/flask_sqlalchemy_session.py
rest_utils/ma/__init__.py
rest_utils/ma/convert.py
rest_utils/ma/model_registry.py
rest_utils/utils/__init__.py
rest_utils/utils/_flask.py
rest_utils/utils/process.py
rest_utils/utils/py.py
rest_utils/worker/__init__.py
rest_utils/worker/fetcher.py
rest_utils/worker/main.py
rest_utils/worker/util.py
rest_utils/worker/worker.py
Rest_Utils-1.2.6.dist-info/METADATA
Rest_Utils-1.2.6.dist-info/WHEEL
Rest_Utils-1.2.6.dist-info/top_level.txt
Rest_Utils-1.2.6.dist-info/RECORD
